Jenkinsfile
MANIFEST.in
README.md
hassmpris-agent.spec
hassmpris-agent.svg
hassmpris-settings.desktop
mypy.ini
pyproject.toml
setup.cfg
tox.ini
src/hassmpris_agent/__init__.py
src/hassmpris_agent/auth.py
src/hassmpris_agent/autodiscovery.py
src/hassmpris_agent/config.py
src/hassmpris_agent/control.py
src/hassmpris_agent/py.typed
src/hassmpris_agent/server.py
src/hassmpris_agent/settings.py
src/hassmpris_agent/verify.py
src/hassmpris_agent.egg-info/PKG-INFO
src/hassmpris_agent.egg-info/SOURCES.txt
src/hassmpris_agent.egg-info/dependency_links.txt
src/hassmpris_agent.egg-info/entry_points.txt
src/hassmpris_agent.egg-info/requires.txt
src/hassmpris_agent.egg-info/top_level.txt
src/hassmpris_agent/mpris/__init__.py
src/hassmpris_agent/mpris/grpc.py
src/hassmpris_agent/mpris/dbus/__init__.py
src/hassmpris_agent/mpris/dbus/chromium.py
src/hassmpris_agent/mpris/dbus/desktop.py
src/hassmpris_agent/mpris/dbus/vlc.py
tests/conftest.py
tests/test_dummy.py