Metadata-Version: 2.1
Name: hassmpris_agent
Version: 0.0.40
Summary: Linux desktop agent to allow MPRIS multimedia control from Home Assistant
Home-page: https://github.com/Rudd-O/hassmpris
Author: Manuel Amador (Rudd-O)
Author-email: rudd-o@rudd-o.com
Classifier: Programming Language :: Python :: 3
Classifier: License :: OSI Approved :: GNU Lesser General Public License v2 (LGPLv2)
Requires-Dist: cryptography
Requires-Dist: dasbus
Requires-Dist: PyGObject
Requires-Dist: pyxdg
Requires-Dist: blindecdh>=0.1.9
Requires-Dist: shortauthstrings>=0.1.8
Requires-Dist: cakes>=0.1.7
Requires-Dist: hassmpris>=0.1.18
Requires-Dist: zeroconf>=0.38.4
Requires-Dist: netifaces>=0.11.0
